basek1/__init__.py
basek1/player.py
basek1/team.py
basek1/team_wl.py
basek1-0.0.0.3.dist-info/METADATA
basek1-0.0.0.3.dist-info/WHEEL
basek1-0.0.0.3.dist-info/top_level.txt
basek1-0.0.0.3.dist-info/RECORD
