Metadata-Version: 2.1
Name: basek1
Version: 0.0.0.3
Summary: testbase
Home-page: 
Author: basekk
Author-email: jino152637@gmail.com
License: MIT
Requires-Python: >=3.4
